{"plum sauce": 0, "berry jam": 1, "blackberry sauce": 2, "mulberry": 3, "black cherry": 4, "plum": 5, "roasted plum": 6, "jam": 7, "sugarplum": 8, "ripe blackberry": 9, "boysenberry": 10, "dark fruit": 11, "black raspberry": 12, "blackcurrant jam": 13, "blackberry jam": 14, "olive tapenade": 15, "sour plum": 16, "marionberry": 17, "blueberry": 18, "berry sauce": 19, "black fruit": 20, "grape jam": 21, "blackberry": 22, "black plum": 23, "wild blueberry": 24, "kalamata olive": 25, "blackcurrant": 26, "bilberry": 27, "acai berry": 28, "hoisin": 29, "black olive": 30, "cassis": 31, "spiced plum": 32, "bramble": 33}