{"exotic spice": 0, "graphite": 1, "wax": 2, "balsamic": 3, "beef broth": 4, "salt": 5, "crushed rocks": 6, "wood ear": 7, "fresh asphalt": 8, "plastic": 9, "dried leaves": 10, "pine bark": 11, "volcanic rock": 12, "wet concrete": 13, "stone": 14, "pencil shavings": 15, "grilled meat": 16, "new leather": 17, "saline": 18, "ash": 19, "mushroom": 20, "wet gravel": 21, "forest mushroom": 22, "game": 23, "cured meat": 24, "petroleum": 25, "rubber": 26, "mushroom broth": 27, "potting soil": 28, "pastrami": 29, "leather": 30, "gun smoke": 31, "charcoal": 32, "truffle": 33, "crushed gravel": 34, "lithium grease": 35, "honeycomb": 36, "wood varnish": 37, "lanolin": 38, "wet asphalt": 39, "rubber cement": 40, "chewing tobacco": 41, "ginger": 42, "honey": 43, "beeswax": 44, "bacon fat": 45, "dessert dust": 46, "candy-cap mushroom": 47, "seashell": 48, "roasted meat": 49, "flint": 50, "tree bark": 51, "smoke": 52, "granite dust": 53, "clay pot": 54, "oolong tea": 55, "wet slate": 56, "slate": 57, "caramel popcorn": 58, "minerals": 59, "chalk": 60, "earthy": 61, "forest floor": 62, "chalk dust": 63, "kerosene": 64, "quinine": 65, "tar": 66, "black truffle": 67, "barbecue smoke": 68, "iron": 69, "smoked meats": 70, "chutney": 71, "barbecue meat": 72, "tobacco leaf": 73, "cocoa": 74, "ground coffee": 75, "citrus oil": 76, "petrichor": 77, "sweet and sour sauce": 78, "clay dust": 79, "underbrush": 80, "incense smoke": 81, "pencil lead": 82}