{"0": "mocha", "1": "toffee", "2": "brown bread", "3": "pie crust", "4": "fresh coconut", "5": "cedar", "6": "butterscotch", "7": "dill", "8": "fudge", "9": "macadamia nut", "10": "baking chocolate", "11": "allspice", "12": "cigar", "13": "toasted marshmallow", "14": "creme brulee", "15": "caramel", "16": "baking spice", "17": "cola", "18": "butter", "19": "clove", "20": "hickory", "21": "sandalwood", "22": "espresso", "23": "sweet tobacco", "24": "coconut oil", "25": "pipe tobacco", "26": "vanilla", "27": "dark chocolate", "28": "pastry", "29": "chocolate", "30": "buttered popcorn", "31": "cigar box", "32": "coffee", "33": "tobacco", "34": "incense", "35": "wood smoke", "36": "wood burner", "37": "camphor", "38": "gingersnap", "39": "cocoa nib", "40": "oak", "41": "brown butter", "42": "milk chocolate", "43": "coconut", "44": "nutmeg"}