{"0": "gardenia", "1": "violet", "2": "dandelion", "3": "dried flowers", "4": "perfume", "5": "iris", "6": "lilac", "7": "daffodil", "8": "peony", "9": "rose water", "10": "orange blossom", "11": "lily", "12": "acacia", "13": "dried rose", "14": "geranium", "15": "magnolia", "16": "baby's breath", "17": "rose petal", "18": "potpourri", "19": "jasmine", "20": "hibiscus", "21": "lavender", "22": "honeysuckle", "23": "elderflower", "24": "apple blossom", "25": "chamomile", "26": "wild iris", "27": "citrus blossom", "28": "rose hip"}