{"0": "kerosene", "1": "chewing tobacco", "2": "quinine", "3": "beeswax", "4": "wet slate", "5": "barbecue smoke", "6": "mushroom", "7": "gun smoke", "8": "roasted meat", "9": "seashell", "10": "wood ear", "11": "honeycomb", "12": "black truffle", "13": "wet concrete", "14": "tobacco leaf", "15": "lithium grease", "16": "grilled meat", "17": "iron", "18": "crushed rocks", "19": "oolong tea", "20": "fresh asphalt", "21": "chutney", "22": "citrus oil", "23": "smoked meats", "24": "incense smoke", "25": "stone", "26": "wet gravel", "27": "crushed gravel", "28": "pastrami", "29": "chalk dust", "30": "cured meat", "31": "dessert dust", "32": "cocoa", "33": "lanolin", "34": "pencil shavings", "35": "petroleum", "36": "clay pot", "37": "truffle", "38": "ground coffee", "39": "ginger", "40": "balsamic", "41": "volcanic rock", "42": "game", "43": "forest floor", "44": "wax", "45": "forest mushroom", "46": "saline", "47": "beef broth", "48": "leather", "49": "pine bark", "50": "candy-cap mushroom", "51": "petrichor", "52": "graphite", "53": "rubber", "54": "granite dust", "55": "wet asphalt", "56": "bacon fat", "57": "ash", "58": "pencil lead", "59": "honey", "60": "plastic", "61": "new leather", "62": "clay dust", "63": "chalk", "64": "minerals", "65": "dried leaves", "66": "tar", "67": "wood varnish", "68": "flint", "69": "salt", "70": "caramel popcorn", "71": "sweet and sour sauce", "72": "mushroom broth", "73": "slate", "74": "smoke", "75": "earthy", "76": "underbrush", "77": "exotic spice", "78": "rubber cement", "79": "charcoal", "80": "potting soil", "81": "tree bark", "82": "barbecue meat"}