{"0": "France", "1": "United_States", "2": "Italy", "3": "Australia", "4": "Spain", "5": "Austria", "6": "Argentina", "7": "New_Zealand", "8": "Germany", "9": "Israel", "10": "Chile", "11": "Croatia", "12": "South_Africa", "13": "Greece", "14": "Portugal", "15": "Mexico", "16": "Lebanon", "17": "Canada", "18": "Hungary", "19": "Moldova", "20": "Georgia", "21": "Slovakia", "22": "Slovenia", "23": "Empty", "24": "Palestinian_Territory,_Occupied", "25": "Switzerland", "26": "Armenia", "27": "Uruguay", "28": "United_Kingdom", "29": "Cyprus", "30": "Bulgaria", "31": "Morocco", "32": "Belarus", "33": "Brazil", "34": "Turkey"}