{"0": "hickory", "1": "coconut oil", "2": "vanilla", "3": "oak", "4": "pie crust", "5": "butter", "6": "chocolate", "7": "coffee", "8": "tobacco", "9": "cigar", "10": "pastry", "11": "cigar box", "12": "cola", "13": "dark chocolate", "14": "sweet tobacco", "15": "brown bread", "16": "baking chocolate", "17": "dill", "18": "cedar", "19": "toffee", "20": "coconut", "21": "wood burner", "22": "caramel", "23": "fudge", "24": "brown butter", "25": "nutmeg", "26": "camphor", "27": "mocha", "28": "wood smoke", "29": "incense", "30": "creme brulee", "31": "macadamia nut", "32": "gingersnap", "33": "sandalwood", "34": "milk chocolate", "35": "butterscotch", "36": "fresh coconut", "37": "espresso", "38": "toasted marshmallow", "39": "pipe tobacco", "40": "buttered popcorn", "41": "allspice", "42": "cocoa nib", "43": "clove", "44": "baking spice"}