{"0": "mace", "1": "curry spice", "2": "aleppo pepper", "3": "mint", "4": "red licorice", "5": "gingerbread", "6": "mustard seed", "7": "candied ginger", "8": "musk", "9": "green herbs", "10": "dried herbs", "11": "dried chili pepper", "12": "juniper", "13": "cinnamon", "14": "menthol", "15": "savory", "16": "oregano", "17": "pink peppercorn", "18": "5-spice powder", "19": "pepper", "20": "licorice", "21": "lemon grass", "22": "cracked pepper", "23": "coriander", "24": "juniper berry", "25": "black licorice", "26": "peppercress", "27": "thyme", "28": "bergamot", "29": "chili pepper", "30": "green peppercorn", "31": "aniseed", "32": "rosemary", "33": "fennel", "34": "anise", "35": "jasmine green tea", "36": "eucalyptus", "37": "star anise", "38": "jalapeno", "39": "matcha powder", "40": "thai basil", "41": "vanilla bean", "42": "matcha", "43": "szechuan peppercorn", "44": "tarragon", "45": "green cardamom", "46": "dried rosemary", "47": "bay leaf", "48": "white pepper", "49": "yerba mate", "50": "dried red chili", "51": "fennel seed", "52": "marjoram", "53": "rooibos", "54": "sage"}