{"oak": 0, "hickory": 1, "fudge": 2, "mocha": 3, "buttered popcorn": 4, "butterscotch": 5, "baking spice": 6, "dill": 7, "coconut oil": 8, "caramel": 9, "tobacco": 10, "nutmeg": 11, "cola": 12, "toasted marshmallow": 13, "brown bread": 14, "dark chocolate": 15, "vanilla": 16, "chocolate": 17, "espresso": 18, "sandalwood": 19, "toffee": 20, "brown butter": 21, "fresh coconut": 22, "wood smoke": 23, "cigar": 24, "cocoa nib": 25, "milk chocolate": 26, "pie crust": 27, "clove": 28, "baking chocolate": 29, "wood burner": 30, "cigar box": 31, "creme brulee": 32, "camphor": 33, "allspice": 34, "sweet tobacco": 35, "coconut": 36, "butter": 37, "incense": 38, "pastry": 39, "pipe tobacco": 40, "gingersnap": 41, "macadamia nut": 42, "cedar": 43, "coffee": 44}