{"0": "rooibos", "1": "juniper berry", "2": "cracked pepper", "3": "green peppercorn", "4": "szechuan peppercorn", "5": "mace", "6": "eucalyptus", "7": "savory", "8": "rosemary", "9": "sage", "10": "matcha powder", "11": "bay leaf", "12": "matcha", "13": "5-spice powder", "14": "musk", "15": "jalapeno", "16": "gingerbread", "17": "licorice", "18": "mint", "19": "red licorice", "20": "dried red chili", "21": "cinnamon", "22": "coriander", "23": "vanilla bean", "24": "marjoram", "25": "true cinnamon", "26": "fennel", "27": "tarragon", "28": "thai basil", "29": "aleppo pepper", "30": "thyme", "31": "oregano", "32": "dried herbs", "33": "lemon grass", "34": "pink peppercorn", "35": "juniper", "36": "mustard seed", "37": "jasmine green tea", "38": "anise", "39": "bergamot", "40": "candied ginger", "41": "yerba mate", "42": "aniseed", "43": "black licorice", "44": "menthol", "45": "chili pepper", "46": "pepper", "47": "fennel seed", "48": "curry spice", "49": "dried rosemary", "50": "peppercress", "51": "green herbs", "52": "dried chili pepper", "53": "white pepper", "54": "star anise", "55": "green cardamom"}