{"pie crust": 0, "toasted marshmallow": 1, "gingersnap": 2, "cocoa nib": 3, "cedar": 4, "brown butter": 5, "chocolate": 6, "sweet tobacco": 7, "fudge": 8, "butterscotch": 9, "brown bread": 10, "incense": 11, "oak": 12, "coconut": 13, "milk chocolate": 14, "macadamia nut": 15, "pastry": 16, "coconut oil": 17, "camphor": 18, "mocha": 19, "coffee": 20, "clove": 21, "espresso": 22, "hickory": 23, "butter": 24, "creme brulee": 25, "toffee": 26, "nutmeg": 27, "cola": 28, "allspice": 29, "baking chocolate": 30, "fresh coconut": 31, "tobacco": 32, "dark chocolate": 33, "dill": 34, "sandalwood": 35, "vanilla": 36, "cigar": 37, "baking spice": 38, "pipe tobacco": 39, "wood burner": 40, "cigar box": 41, "buttered popcorn": 42, "caramel": 43, "wood smoke": 44}